pytest_beakerlib.py
pytest_beakerlib-0.7.1.dist-info/DESCRIPTION.rst
pytest_beakerlib-0.7.1.dist-info/METADATA
pytest_beakerlib-0.7.1.dist-info/RECORD
pytest_beakerlib-0.7.1.dist-info/WHEEL
pytest_beakerlib-0.7.1.dist-info/entry_points.txt
pytest_beakerlib-0.7.1.dist-info/metadata.json
pytest_beakerlib-0.7.1.dist-info/top_level.txt
