Metadata-Version: 2.0
Name: pytest-beakerlib
Version: 0.7.1
Summary: A pytest plugin that reports test results to the BeakerLib framework
Home-page: https://pagure.io/python-pytest-beakerlib
Author: Petr Viktorin
Author-email: pviktori@redhat.com
License: GPL
Platform: UNKNOWN
Classifier: Development Status :: 5 - Production/Stable
Classifier: License :: OSI Approved :: GNU General Public License v3 or later (GPLv3+)
Classifier: Operating System :: POSIX
Classifier: Programming Language :: Python
Classifier: Programming Language :: Python :: 2.7
Classifier: Topic :: Software Development :: Quality Assurance
Requires-Dist: pytest
